aiwall/KhojWallpaper.plist
aiwall/__init__.py
aiwall/paper.py
ai_wallpaper-0.1.dev19.dist-info/METADATA
ai_wallpaper-0.1.dev19.dist-info/WHEEL
ai_wallpaper-0.1.dev19.dist-info/entry_points.txt
ai_wallpaper-0.1.dev19.dist-info/licenses/AUTHORS
ai_wallpaper-0.1.dev19.dist-info/licenses/LICENSE
ai_wallpaper-0.1.dev19.dist-info/RECORD
