Metadata-Version: 2.4
Name: ai-wallpaper
Version: 0.1.dev19
Summary: Create fresh, personal AI painted wallpapers
Project-URL: Homepage, https://github.com/debanjum/ai-wallpaper
Author: Debanjum Singh Solanky
License-Expression: GPL-3.0-or-later
License-File: AUTHORS
License-File: LICENSE
Keywords: AI,images,khoj
Classifier: Development Status :: 4 - Beta
Classifier: Intended Audience :: Information Technology
Classifier: License :: OSI Approved :: GNU General Public License v3 or later (GPLv3+)
Classifier: Operating System :: OS Independent
Classifier: Programming Language :: Python :: 3
Classifier: Programming Language :: Python :: 3.9
Classifier: Programming Language :: Python :: 3.10
Classifier: Programming Language :: Python :: 3.11
Classifier: Programming Language :: Python :: 3.12
Classifier: Topic :: Adaptive Technologies
Classifier: Topic :: Artistic Software
Classifier: Topic :: Scientific/Engineering :: Artificial Intelligence
Requires-Python: >=3.9
Requires-Dist: requests>=2.26.0
Requires-Dist: rich>=13.3.1
Provides-Extra: dev
Requires-Dist: black>=23.1.0; extra == 'dev'
Requires-Dist: mypy>=1.0.1; extra == 'dev'
Requires-Dist: pre-commit>=3.0.4; extra == 'dev'
Requires-Dist: pytest>=7.1.2; extra == 'dev'
